jdbase_client/__init__.py
jdbase_client-1.0.1.dist-info/METADATA
jdbase_client-1.0.1.dist-info/WHEEL
jdbase_client-1.0.1.dist-info/top_level.txt
jdbase_client-1.0.1.dist-info/RECORD
