Metadata-Version: 2.1
Name: jdbase-client
Version: 1.0.1
Summary: jdbase-client is a ORM for JDBase
Home-page: https://github.com/rakibmia7254/jdbabe-client
Author: Rakib Hossain
Author-email: rakib4ggp@gmail.com
Classifier: Development Status :: 5 - Production/Stable
Classifier: Intended Audience :: Developers
Classifier: License :: OSI Approved :: MIT License
Classifier: Programming Language :: Python :: 3
Classifier: Programming Language :: Python :: 3.6
Classifier: Programming Language :: Python :: 3.7
Classifier: Programming Language :: Python :: 3.8
Requires-Dist: requests
